src/__init__.py
src/run.py
poker_tracker-0.1.dist-info/LICENSE
poker_tracker-0.1.dist-info/METADATA
poker_tracker-0.1.dist-info/WHEEL
poker_tracker-0.1.dist-info/top_level.txt
poker_tracker-0.1.dist-info/RECORD
