Metadata-Version: 2.1
Name: poker-tracker
Version: 0.1
Summary: A package to track poker results
Home-page: UNKNOWN
Author: Joewe Low
License: UNKNOWN
Platform: UNKNOWN
License-File: LICENSE
